dagster_ibis/__init__.py
dagster_ibis/client.py
dagster_ibis/io_manager.py
dagster_ibis/type_handler.py
dagster_ibis-0.1.6.dist-info/METADATA
dagster_ibis-0.1.6.dist-info/WHEEL
dagster_ibis-0.1.6.dist-info/RECORD
