Metadata-Version: 2.4
Name: dagster-ibis
Version: 0.1.6
Summary: Base library for interacting with Ibis Tables within dagster.
Author-email: James Blackwell <33688964+j-blackwell@users.noreply.github.com>
Requires-Python: >=3.10
Requires-Dist: dagster-duckdb>=0.23.6
Requires-Dist: dagster>=1.8
Requires-Dist: ibis-framework>=10.3.1
